learning_pkg/__init__.py
learning_pkg/one.py
learning_pkg-1.0.0.dist-info/METADATA
learning_pkg-1.0.0.dist-info/WHEEL
learning_pkg-1.0.0.dist-info/licenses/LICENSE.md
learning_pkg-1.0.0.dist-info/RECORD
